CHANGES.rst
COPYING.LGPLv3
MANIFEST.in
README.rst
setup.py
deep_serializer/__init__.py
deep_serializer/api.py
deep_serializer/base.py
deep_serializer/exceptions.py
deep_serializer/json_serializer.py
deep_serializer/python_serializer.py
deep_serializer/settings.py
deep_serializer/utils.py
deep_serializer/xml_serializer.py
deep_serializer/yaml_serializer.py
deep_serializer/serializers/__init__.py
deep_serializer/serializers/base.py
deep_serializer/serializers/json.py
deep_serializer/serializers/python.py
deep_serializer/serializers/pyyaml.py
deep_serializer/serializers/xml_serializer.py
django_deep_serializer.egg-info/PKG-INFO
django_deep_serializer.egg-info/SOURCES.txt
django_deep_serializer.egg-info/dependency_links.txt
django_deep_serializer.egg-info/not-zip-safe
django_deep_serializer.egg-info/top_level.txt