Metadata-Version: 1.1
Name: django-deep-serializer
Version: 0.1.2
Summary: Serialize/Deserialize an object and its relations through class definitions
Home-page: https://github.com/goinnn/django-deep-serializer
Author: Pablo Martin
Author-email: goinnn@gmail.com
License: LGPL 3
Keywords: django,serializer,deep,deep serializer,deserialize,deep deserialize
Platform: UNKNOWN
Classifier: Development Status :: 4 - Beta
Classifier: Framework :: Django
Classifier: License :: OSI Approved :: GNU Library or Lesser General Public License (LGPL)
